coverlib/__init__.py
coverlib/api.py
coverlib/cache.py
coverlib/cli.py
coverlib/combinatorics.py
coverlib/fetchers.py
coverlib/optimizer.py
coverlib/repair.py
multiarrangement/Audio.png
multiarrangement/__init__.py
multiarrangement/cli.py
multiarrangement/experiment_runner.py
multiarrangement/optimize_cover_flex.py
multiarrangement/optimize_cover_pure.py
multiarrangement/results.py
multiarrangement/test_audio_icon_new.png
multiarrangement/try.py
multiarrangement/15audios/BirdNET_01_XC169082.wav
multiarrangement/15audios/BirdNET_02_XC109300.wav
multiarrangement/15audios/BirdNET_03_ML73875.wav
multiarrangement/15audios/BirdNET_04_ML10157.wav
multiarrangement/15audios/BirdNET_05_XC350304.wav
multiarrangement/15audios/BirdNET_06_XC190347.wav
multiarrangement/15audios/BirdNET_07_ML11308.wav
multiarrangement/15audios/BirdNET_08_XC313331.wav
multiarrangement/15audios/BirdNET_09_ML62779.wav
multiarrangement/15audios/BirdNET_10_XC154555.wav
multiarrangement/15audios/BirdNET_11_XC42442.wav
multiarrangement/15audios/BirdNET_12_XC419704.wav
multiarrangement/15audios/BirdNET_13_ML176154.wav
multiarrangement/15audios/BirdNET_14_ML73990.wav
multiarrangement/15audios/BirdNET_15_XC104666.wav
multiarrangement/15images/1.png
multiarrangement/15images/10.png
multiarrangement/15images/11.png
multiarrangement/15images/12.png
multiarrangement/15images/13.png
multiarrangement/15images/14.png
multiarrangement/15images/15.png
multiarrangement/15images/2.png
multiarrangement/15images/3.png
multiarrangement/15images/4.png
multiarrangement/15images/5.png
multiarrangement/15images/6.png
multiarrangement/15images/7.png
multiarrangement/15images/8.png
multiarrangement/15images/9.png
multiarrangement/15videos/002_M.avi
multiarrangement/15videos/004_F.avi
multiarrangement/15videos/005_M.avi
multiarrangement/15videos/007_F.avi
multiarrangement/15videos/008_M.avi
multiarrangement/15videos/012_F.avi
multiarrangement/15videos/013_M.avi
multiarrangement/15videos/015_F.avi
multiarrangement-0.1.10.2.dist-info/licenses/LICENSE
multiarrangement-0.1.10.2.dist-info/METADATA
multiarrangement-0.1.10.2.dist-info/WHEEL
multiarrangement-0.1.10.2.dist-info/entry_points.txt
multiarrangement-0.1.10.2.dist-info/top_level.txt
multiarrangement-0.1.10.2.dist-info/RECORD
