Metadata-Version: 2.4
Name: multiarrangement
Version: 0.1.10.2
Summary: Video & audio similarity arrangement toolkit (set-cover and adaptive LTW)
Author: Umur Yıldız
License-Expression: MIT
Project-URL: Homepage, https://github.com/UYildiz12/Multiarrangement-for-videos
Project-URL: Repository, https://github.com/UYildiz12/Multiarrangement-for-videos
Project-URL: Documentation, https://github.com/UYildiz12/Multiarrangement-for-videos#readme
Project-URL: Bug Tracker, https://github.com/UYildiz12/Multiarrangement-for-videos/issues
Keywords: psychology,experiment,video,similarity,multiarrangement,rdm
Classifier: Development Status :: 4 - Beta
Classifier: Intended Audience :: Science/Research
Classifier: Topic :: Scientific/Engineering
Classifier: Programming Language :: Python :: 3
Classifier: Programming Language :: Python :: 3.8
Classifier: Programming Language :: Python :: 3.9
Classifier: Programming Language :: Python :: 3.10
Classifier: Programming Language :: Python :: 3.11
Classifier: Programming Language :: Python :: 3.12
Classifier: Operating System :: OS Independent
Requires-Python: >=3.8
License-File: LICENSE
Requires-Dist: numpy>=1.20.0
Requires-Dist: pandas>=1.3.0
Requires-Dist: pygame>=2.0.0
Requires-Dist: opencv-python>=4.5.0
Requires-Dist: openpyxl>=3.0.0
Requires-Dist: matplotlib>=3.4.0
Provides-Extra: dev
Requires-Dist: pytest>=6.0; extra == "dev"
Requires-Dist: pytest-cov; extra == "dev"
Requires-Dist: black; extra == "dev"
Requires-Dist: flake8; extra == "dev"
Requires-Dist: mypy; extra == "dev"
Provides-Extra: coverlib
Requires-Dist: urllib3; extra == "coverlib"
Requires-Dist: requests; extra == "coverlib"
Dynamic: license-file
